kriptex/__init__.py
kriptex/encryption.py
kriptex/kriptex_app.py
kriptex/main.py
kriptex-0.2.0.dist-info/LICENSE
kriptex-0.2.0.dist-info/METADATA
kriptex-0.2.0.dist-info/WHEEL
kriptex-0.2.0.dist-info/entry_points.txt
kriptex-0.2.0.dist-info/top_level.txt
kriptex-0.2.0.dist-info/RECORD
