Metadata-Version: 2.2
Name: kriptex
Version: 0.2.0
Summary: Kriptex symbol encryption library
Home-page: https://github.com/Azccriminal/kriptex
Author: Zaman Huseyinli
Author-email: zamanhuseynli23@gmail.com
Classifier: Programming Language :: Python :: 3
Classifier: License :: OSI Approved :: BSD License
Classifier: Operating System :: OS Independent
Requires-Python: >=3.6
License-File: LICENSE
Requires-Dist: pycryptodome
Requires-Dist: requests
Requires-Dist: PyQt6
Dynamic: author
Dynamic: author-email
Dynamic: classifier
Dynamic: description
Dynamic: description-content-type
Dynamic: home-page
Dynamic: requires-dist
Dynamic: requires-python
Dynamic: summary
